otto_tts/__init__.py
otto_tts/cli.py
otto_tts/constants.py
otto_tts/lib.py
otto_tts-0.1.2.dist-info/METADATA
otto_tts-0.1.2.dist-info/WHEEL
otto_tts-0.1.2.dist-info/entry_points.txt
otto_tts-0.1.2.dist-info/top_level.txt
otto_tts-0.1.2.dist-info/RECORD
