Metadata-Version: 2.4
Name: otto-tts
Version: 0.1.2
Summary: A command line tool for otto's text-to-speech service from shuodedao.li
Project-URL: repository, https://github.com/lvlh2/otto-tts
Requires-Python: >=3.13
Requires-Dist: audioop-lts>=0.2.2
Requires-Dist: click>=8.3.0
Requires-Dist: httpx>=0.28.1
Requires-Dist: pydub>=0.25.1
Requires-Dist: tqdm>=4.67.1
